anime_relations_py/__init__.py
anime_relations_py/file_parser.py
anime_relations_py/rule.py
anime_relations_py-0.1.2.dist-info/LICENSE.md
anime_relations_py-0.1.2.dist-info/METADATA
anime_relations_py-0.1.2.dist-info/WHEEL
anime_relations_py-0.1.2.dist-info/top_level.txt
anime_relations_py-0.1.2.dist-info/RECORD
