Metadata-Version: 2.1
Name: anime-relations-py
Version: 0.1.2
Summary: A parser for anime-relations. So you don't have to.
Home-page: https://github.com/tylergibbs2/anime-relations-py
Author: Tyler
License: MIT
Project-URL: Documentation, https://github.com/tylergibbs2/anime-relations-py/blob/master/README.md
Project-URL: Issue tracker, https://github.com/tylergibbs2/anime-relations-py/issues
Classifier: License :: OSI Approved :: MIT License
Classifier: Intended Audience :: Developers
Classifier: Natural Language :: English
Classifier: Operating System :: OS Independent
Classifier: Programming Language :: Python :: 3.6
Classifier: Programming Language :: Python :: 3.7
Classifier: Programming Language :: Python :: 3.8
Classifier: Programming Language :: Python :: 3.9
Classifier: Topic :: Internet
Classifier: Topic :: Software Development :: Libraries
Classifier: Topic :: Software Development :: Libraries :: Python Modules
Classifier: Topic :: Utilities
Requires-Python: >=3.6
License-File: LICENSE.md
Requires-Dist: aiohttp (>=3.7.4)
Requires-Dist: requests (>=2.25.1)
